pyhumitemp/__init__.py
pyhumitemp/pyHumiTemp.py
pyhumitemp-1.0.1.post1.dist-info/METADATA
pyhumitemp-1.0.1.post1.dist-info/RECORD
pyhumitemp-1.0.1.post1.dist-info/WHEEL
pyhumitemp-1.0.1.post1.dist-info/top_level.txt
