Metadata-Version: 2.1
Name: pyhumitemp
Version: 1.0.1.post1
Summary: Script to capture numeric humidity and temperature output from DHT22
Home-page: https://github.com/viharm/pyHumiTemp
Author: Viharm
Author-email: viharm@malviya.net
License: UNKNOWN
Project-URL: Bug Reports, https://github.com/viharm/pyHumiTemp/issues
Project-URL: Source, https://github.com/viharm/pyHumiTemp
Keywords: python humidity temperature iot terminal dht22
Platform: UNKNOWN
Classifier: Programming Language :: Python
Classifier: License :: Other/Proprietary License
Classifier: Operating System :: POSIX
Classifier: Development Status :: 5 - Production/Stable
Classifier: Environment :: Console
Classifier: Intended Audience :: Developers
Classifier: Intended Audience :: End Users/Desktop
Classifier: Natural Language :: English
Classifier: Topic :: System :: Hardware
Classifier: Topic :: System :: Monitoring
Classifier: Topic :: Terminals
Classifier: Topic :: Utilities
